maltego_crypto_test.py
maltego_crypto_test-0.1.9.dist-info/LICENSE
maltego_crypto_test-0.1.9.dist-info/WHEEL
maltego_crypto_test-0.1.9.dist-info/METADATA
maltego_crypto_test-0.1.9.dist-info/RECORD
